torchstat/__init__.py
torchstat/__main__.py
torchstat/compute_flops.py
torchstat/compute_madd.py
torchstat/model_hook.py
torchstat/reporter.py
torchstat/stat_tree.py
torchstat/statistics.py
torchstat-0.0.6.dist-info/METADATA
torchstat-0.0.6.dist-info/RECORD
torchstat-0.0.6.dist-info/WHEEL
torchstat-0.0.6.dist-info/entry_points.txt
torchstat-0.0.6.dist-info/top_level.txt
