Metadata-Version: 2.1
Name: torchstat
Version: 0.0.6
Summary: torchstat: The Pytorch Model Analyzer.
Home-page: https://github.com/Swall0w/torchstat
Author: Swall0w
License: Type license() to see the full license text
Platform: UNKNOWN
Requires-Dist: torch
Requires-Dist: numpy
Requires-Dist: pandas
